zsender/__init__.py
zsender-1.2.7.dist-info/METADATA
zsender-1.2.7.dist-info/WHEEL
zsender-1.2.7.dist-info/top_level.txt
zsender-1.2.7.dist-info/RECORD
